allah/__init__.py
allah/blessings.py
allah-0.1.2.dist-info/METADATA
allah-0.1.2.dist-info/WHEEL
allah-0.1.2.dist-info/top_level.txt
allah-0.1.2.dist-info/RECORD
