Metadata-Version: 2.1
Name: allah
Version: 0.1.2
Summary: Recieve blessings from allah
Author: Adarsh
